tap_canvas_temple/__init__.py
tap_canvas_temple/cli.py
tap_canvas_temple/client.py
tap_canvas_temple/streams.py
tap_canvas_temple/tap.py
tap_canvas_temple/tests/__init__.py
tap_canvas_temple/tests/test_core.py
tap_canvas_temple/typing.py
tap_canvas_temple-0.0.4.dist-info/entry_points.txt
tap_canvas_temple-0.0.4.dist-info/METADATA
tap_canvas_temple-0.0.4.dist-info/WHEEL
tap_canvas_temple-0.0.4.dist-info/RECORD
